Libdoc2Text/__init__.py
Libdoc2Text/__main__.py
Libdoc2Text/libdoc2text.py
Libdoc2Text/templates/library.adoc.jinja
Libdoc2Text/templates/library.md.jinja
robotframework_libdoc2text-1.0.1.dist-info/entry_points.txt
robotframework_libdoc2text-1.0.1.dist-info/LICENSE
robotframework_libdoc2text-1.0.1.dist-info/WHEEL
robotframework_libdoc2text-1.0.1.dist-info/METADATA
robotframework_libdoc2text-1.0.1.dist-info/RECORD
