Metadata-Version: 2.1
Name: robotframework-libdoc2text
Version: 1.0.1
Summary: Generate library documentation in plain text from the JSON generated by libdoc
Author-email: Marduk Bolaños <marduk.bolanos@imbus.de>
Requires-Python: >= 3.8.2
Requires-Dist: jinja2>=3.1.3
Requires-Dist: click>=8.1.7
Project-URL: homepage, https://github.com/mardukbp/robotframework-libdoc2text
